[
  {
    "id": 3738037,
    "title": "Grace4Joy",
    "price": 94.36,
    "currency": "SGD",
    "image_url": "https://m.media-amazon.com/images/I/61N8sJ2FceL._AC_UL320_.jpg",
    "brand": "",
    "rating": 5.00,
    "review_count": 223,
    "source": "amazon_sg",
    "merchant_id": "amazon_sg",
    "category": "wall art",
    "url": "https://www.amazon.sg/dp/B0DD3MYVH9"
  },
  {
    "id": 2711369,
    "title": "Monster Jam, Official Sparkle Smash Monster Truck, Die-Cast Vehicle, 1:64 Scale, Kids Toys for Boys Ages 3 and up",
    "price": 31.30,
    "currency": "SGD",
    "image_url": "https://m.media-amazon.com/images/I/917Fh2A1-gL._AC_UL320_.jpg",
    "brand": "Monster",
    "rating": 5.00,
    "review_count": 154,
    "source": "amazon_sg",
    "merchant_id": "amazon_sg",
    "category": "jam",
    "url": "https://www.amazon.sg/dp/B0DWQ57JMZ"
  },
  {
    "id": 2557808,
    "title": "Maelstrom",
    "price": 43.78,
    "currency": "SGD",
    "image_url": "https://m.media-amazon.com/images/I/61zzjJ-sIvL._AC_UL320_.jpg",
    "brand": "Maelstrom",
    "rating": 5.00,
    "review_count": 127,
    "source": "amazon_sg",
    "merchant_id": "amazon_sg",
    "category": "backpack",
    "url": "https://www.amazon.sg/dp/B0FQ5P2Z7B"
  },
  {
    "id": 2558449,
    "title": "Maelstrom",
    "price": 54.32,
    "currency": "SGD",
    "image_url": "https://m.media-amazon.com/images/I/615YyhN6wrL._AC_UL320_.jpg",
    "brand": "Maelstrom",
    "rating": 5.00,
    "review_count": 127,
    "source": "amazon_sg",
    "merchant_id": "amazon_sg",
    "category": "luggage",
    "url": "https://www.amazon.sg/dp/B0FQ5P7XQ2"
  },
  {
    "id": 2548527,
    "title": "Copper Pearl",
    "price": 45.25,
    "currency": "SGD",
    "image_url": "https://m.media-amazon.com/images/I/91lovNfnfML._AC_UL320_.jpg",
    "brand": "Copper",
    "rating": 5.00,
    "review_count": 120,
    "source": "amazon_sg",
    "merchant_id": "amazon_sg",
    "category": "blanket",
    "url": "https://www.amazon.sg/dp/B08CM97V1K"
  },
  {
    "id": 2536480,
    "title": "Business is War: AI is the New Weapon",
    "price": 32.79,
    "currency": "SGD",
    "image_url": "https://m.media-amazon.com/images/I/61nuHtHP7dL._AC_UL320_.jpg",
    "brand": "Business",
    "rating": 5.00,
    "review_count": 107,
    "source": "amazon_sg",
    "merchant_id": "amazon_sg",
    "category": "business books",
    "url": "https://www.amazon.sg/dp/B0FPCZHKM7"
  },
  {
    "id": 2518978,
    "title": "Beyond Belief: The Science-backed Way to Stop Limiting Yourself and Achieve Breakthrough Results",
    "price": 34.60,
    "currency": "SGD",
    "image_url": "https://m.media-amazon.com/images/I/715VCA0WGlL._AC_UL320_.jpg",
    "brand": "Beyond",
    "rating": 5.00,
    "review_count": 103,
    "source": "amazon_sg",
    "merchant_id": "amazon_sg",
    "category": "psychology books",
    "url": "https://www.amazon.sg/dp/0593852036"
  },
  {
    "id": 2551634,
    "title": "Kids Silverware with Feelings - Stainless Steel Utensils, Cutlery Set for Kids 3 Years Old+, Knife + Spoon + Fork for Toddlers, Tableware Eating Dish 4 Lunch Box Forks and Spoons (Pink)",
    "price": 15.67,
    "currency": "SGD",
    "image_url": "https://m.media-amazon.com/images/I/71ZTIqIUgQL._AC_UL320_.jpg",
    "brand": "Kids",
    "rating": 5.00,
    "review_count": 99,
    "source": "amazon_sg",
    "merchant_id": "amazon_sg",
    "category": "cutlery set",
    "url": "https://www.amazon.sg/dp/B0D2S3QPYN"
  },
  {
    "id": 3771410,
    "title": "NBA Jam",
    "price": 23.00,
    "currency": "SGD",
    "image_url": "https://m.media-amazon.com/images/I/61rRaxNsCsL._AC_UL320_.jpg",
    "brand": "NBA",
    "rating": 5.00,
    "review_count": 96,
    "source": "amazon_sg",
    "merchant_id": "amazon_sg",
    "category": "jam",
    "url": "https://www.amazon.sg/dp/1940535204"
  },
  {
    "id": 3776701,
    "title": "BESDEAR",
    "price": 26.23,
    "currency": "SGD",
    "image_url": "https://m.media-amazon.com/images/I/71lLanScmhL._AC_UL320_.jpg",
    "brand": "BESDEAR",
    "rating": 5.00,
    "review_count": 91,
    "source": "amazon_sg",
    "merchant_id": "amazon_sg",
    "category": "baby clothes",
    "url": "https://www.amazon.sg/dp/B0CSPM7YZL"
  },
  {
    "id": 2550108,
    "title": "Candle Warmer Lamp with Timer, Birthday Gifts for Women Mom, Height Adjustable Wax Melts Warmer, House Warming Gifts New Home Decor, Dimmable Candle Warmer for Jar Candles with 2 Bulbs",
    "price": 67.47,
    "currency": "SGD",
    "image_url": "https://m.media-amazon.com/images/I/7121RByD4uL._AC_UL320_.jpg",
    "brand": "Candle",
    "rating": 5.00,
    "review_count": 88,
    "source": "amazon_sg",
    "merchant_id": "amazon_sg",
    "category": "candle",
    "url": "https://www.amazon.sg/dp/B0FHPN5NQR"
  },
  {
    "id": 2524541,
    "title": "Disney The Art of Zootopia 2",
    "price": 96.87,
    "currency": "SGD",
    "image_url": "https://m.media-amazon.com/images/I/81PWtS3VXkL._AC_UL320_.jpg",
    "brand": "Disney",
    "rating": 5.00,
    "review_count": 84,
    "source": "amazon_sg",
    "merchant_id": "amazon_sg",
    "category": "art books",
    "url": "https://www.amazon.sg/dp/1797233629"
  }
]